gisweb_jppa/__init__.py
gisweb_jppa/jppa_wsdl.py
gisweb_jppa/pagopa.py
gisweb_jppa/schema.py
gisweb_jppa/templates/CreaAvvisoPagamento.xml
gisweb_jppa/templates/Debito.xml
gisweb_jppa/templates/EliminaAvvisoPagamento.xml
gisweb_jppa/templates/InfoAvvisoPagamentoPerChiaveDebito.xml
gisweb_jppa/templates/InfoPagamentoDebito.xml
gisweb_jppa/templates/PagaDebiti.xml
gisweb_jppa/templates/SoapResponse.xml
gisweb_jppa/templates/Soggetto.xml
gisweb_jppa/templates/serviceCall.xml
gisweb_jppa/templates/wsdl_notifica.xml
gisweb_jppa-0.6.dist-info/LICENSE
gisweb_jppa-0.6.dist-info/METADATA
gisweb_jppa-0.6.dist-info/WHEEL
gisweb_jppa-0.6.dist-info/RECORD
