Metadata-Version: 2.3
Name: gisweb-jppa
Version: 0.6
Summary: 
Author: Roberto Starnini
Author-email: roberto.starnini@gmail.com
Requires-Python: >3.10,<3.13
Classifier: Programming Language :: Python :: 3
Classifier: Programming Language :: Python :: 3.11
Classifier: Programming Language :: Python :: 3.12
Requires-Dist: gisweb-pagopa-schema (>=0.3,<0.4)
Requires-Dist: httpx (>=0.28.1,<0.29.0)
Requires-Dist: jinja2 (>=3.1.2,<4.0.0)
Requires-Dist: pydantic[dotenv,email] (>=2.3.0,<3.0.0)
Requires-Dist: pyjwt[crypto] (>=2.8.0,<3.0.0)
Requires-Dist: requests (>=2.31.0,<3.0.0)
